w3mo/__init__.py
w3mo/__main__.py
w3mo/w3mo.py
w3mo-0.1.10.dist-info/LICENSE
w3mo-0.1.10.dist-info/METADATA
w3mo-0.1.10.dist-info/WHEEL
w3mo-0.1.10.dist-info/top_level.txt
w3mo-0.1.10.dist-info/RECORD
