Metadata-Version: 2.1
Name: w3mo
Version: 0.1.10
Summary: wemo control library
Home-page: https://github.com/mghelton/w3mo
Author: Gage Helton
Author-email: gagehelton@gmail.com
License: UNKNOWN
Platform: UNKNOWN
Classifier: Programming Language :: Python :: 3
Classifier: License :: OSI Approved :: MIT License
Classifier: Operating System :: OS Independent
Requires-Dist: requests (==2.23.0)
